devdraft_sdk/__init__.py
devdraft_sdk/api_client.py
devdraft_sdk/configuration.py
devdraft_sdk/customer_utils.py
devdraft_sdk/rest.py
devdraft_sdk/sdk_utils.py
devdraft_sdk/api/__init__.py
devdraft_sdk/api/api_health_api.py
devdraft_sdk/api/app_balances_api.py
devdraft_sdk/api/customers_api.py
devdraft_sdk/api/exchange_rates_api.py
devdraft_sdk/api/invoices_api.py
devdraft_sdk/api/liquidation_addresses_api.py
devdraft_sdk/api/payment_intents_api.py
devdraft_sdk/api/payment_links_api.py
devdraft_sdk/api/products_api.py
devdraft_sdk/api/taxes_api.py
devdraft_sdk/api/test_payments_api.py
devdraft_sdk/api/transfers_api.py
devdraft_sdk/api/wallets_api.py
devdraft_sdk/api/webhooks_api.py
devdraft_sdk/models/__init__.py
devdraft_sdk/models/aggregated_balance_response.py
devdraft_sdk/models/all_balances_response.py
devdraft_sdk/models/all_of_all_balances_response_eurc.py
devdraft_sdk/models/all_of_all_balances_response_usdc.py
devdraft_sdk/models/all_of_create_bank_payment_intent_dto_destination_currency.py
devdraft_sdk/models/all_of_create_bank_payment_intent_dto_destination_network.py
devdraft_sdk/models/all_of_create_bank_payment_intent_dto_source_currency.py
devdraft_sdk/models/all_of_create_bank_payment_intent_dto_source_payment_rail.py
devdraft_sdk/models/all_of_create_customer_dto_status.py
devdraft_sdk/models/all_of_create_liquidation_address_dto_destination_currency.py
devdraft_sdk/models/all_of_create_liquidation_address_dto_destination_payment_rail.py
devdraft_sdk/models/all_of_create_stable_payment_intent_dto_destination_currency.py
devdraft_sdk/models/all_of_create_stable_payment_intent_dto_destination_network.py
devdraft_sdk/models/all_of_create_stable_payment_intent_dto_source_currency.py
devdraft_sdk/models/all_of_create_stable_payment_intent_dto_source_network.py
devdraft_sdk/models/all_of_update_customer_dto_status.py
devdraft_sdk/models/bridge_payment_rail.py
devdraft_sdk/models/create_bank_payment_intent_dto.py
devdraft_sdk/models/create_customer_dto.py
devdraft_sdk-1.0.9.dist-info/METADATA
devdraft_sdk-1.0.9.dist-info/WHEEL
devdraft_sdk-1.0.9.dist-info/top_level.txt
devdraft_sdk-1.0.9.dist-info/RECORD
