Metadata-Version: 2.4
Name: devdraft-sdk
Version: 1.0.9
Summary: Devdraft SDK - A Python library for Devdraft's Payment & Business Management API
Home-page: https://github.com/devdraftengineer/devdraft-sdk-python
Author-email: engineering@devdraft.ai
Keywords: Swagger,Devdraft Payment &amp; Business Management API
Requires-Dist: urllib3>=1.15
Requires-Dist: six>=1.10
Requires-Dist: certifi
Requires-Dist: python-dateutil
Dynamic: author-email
Dynamic: description
Dynamic: description-content-type
Dynamic: home-page
Dynamic: keywords
Dynamic: requires-dist
Dynamic: summary
